qsim/NISQsim.py
qsim/Qsim.py
qsim/__init__.py
qsim/qSimException.py
qsim/qgates.py
qsim/qgatesUtils.py
qsimulator-1.5.data/scripts/qcli.py
qsimulator-1.5.dist-info/LICENSE
qsimulator-1.5.dist-info/METADATA
qsimulator-1.5.dist-info/WHEEL
qsimulator-1.5.dist-info/top_level.txt
qsimulator-1.5.dist-info/RECORD
