Metadata-Version: 2.1
Name: qsimulator
Version: 1.5
Summary: Quantum computer simulator
Author: Atul Varshneya
Author-email: atul.varshneya@gmail.com
License: GPL
Keywords: qsystems quantum computing
License-File: LICENSE
Requires-Dist: numpy
